[{"id":1,"o":35892,"text":"Papir/output","url":"paper_output.html","node":"0","children":[{"id":2,"o":35445,"text":"Opgavetype","url":"job_type.html","node":"0+0","children":[{"id":3,"o":19395,"text":"Almindelig udskrivning","url":"normal_print.html","node":"0+0+0","leaf":true},{"id":4,"o":29767,"text":"Indstilling for fortrolig udskrivning","url":"secure_print.html","node":"0+0+1","leaf":true},{"id":5,"o":19931,"text":"Tilbagehold opgave","url":"hold_job.html","node":"0+0+2","leaf":true},{"id":6,"o":35936,"text":"Gemt opgave","url":"saved_job.html","node":"0+0+3","leaf":true},{"id":7,"o":19920,"text":"Gemt baggrundsformular","url":"saved_background_form.html","node":"0+0+4","leaf":true}]},{"id":8,"o":35695,"text":"Papir","url":"paper.html","node":"0+1","children":[{"id":9,"o":28670,"text":"Papirnavn","url":"named_paper.html","node":"0+1+0","children":[{"id":10,"o":28671,"text":"Indstillinger for Papirnavn","url":"named_paper_options.html","node":"0+1+0+0","leaf":true}]},{"id":11,"o":19396,"text":"Papirfarve","url":"other_color.html","node":"0+1+1","children":[{"id":12,"o":35253,"text":"Oprettelse af brugerdefineret papirfarve","url":"custom_color.html","node":"0+1+1+0","leaf":true}]},{"id":13,"o":19945,"text":"Papirtype","url":"other_type.html","node":"0+1+2","children":[{"id":14,"o":35278,"text":"Oprettelse af brugerdefineret papirtype","url":"custom_type.html","node":"0+1+2+0","leaf":true},{"id":15,"o":35426,"text":"Faneblade","url":"pre_cut_tabs.html","node":"0+1+2+1","leaf":true},{"id":16,"o":35424,"text":"Forsorteret papirtype","url":"sequenced_paper_type.html","node":"0+1+2+2","leaf":true}]},{"id":17,"o":19947,"text":"Papirvægt","url":"other_weight.html","node":"0+1+3","children":[{"id":18,"o":35276,"text":"Oprettelse af brugerdefineret papirvægt","url":"custom_weight.html","node":"0+1+3+0","leaf":true}]},{"id":19,"o":19919,"text":"Avanceret papirvalg","url":"advanced_paper_selection.html","node":"0+1+4","children":[{"id":20,"o":35277,"text":"Oprettelse af brugerdefineret papirformat","url":"custom_size.html","node":"0+1+4+0","leaf":true}]}]},{"id":21,"o":35921,"text":"1- eller 2-sidet","url":"2_sided_printing.html","node":"0+2","leaf":true},{"id":22,"o":19948,"text":"Outputfarve","url":"output_color.html","node":"0+3","leaf":true},{"id":23,"o":36041,"text":"Efterbehandling","url":"finishing.html","node":"0+4","children":[{"id":24,"o":19595,"text":"Hæftning","url":"stapling.html","node":"0+4+0","leaf":true},{"id":25,"o":19593,"text":"Hulning","url":"punching.html","node":"0+4+1","leaf":true},{"id":26,"o":19591,"text":"Foldning","url":"folding.html","node":"0+4+2","children":[{"id":27,"o":35428,"text":"Firkantet foldning","url":"square_fold.html","node":"0+4+2+0","leaf":true},{"id":28,"o":35436,"text":"Beskær den yderste kant","url":"trim_outside_edge.html","node":"0+4+2+1","leaf":true}]},{"id":29,"o":35926,"text":"Perfect Binder","url":"perfect_binder.html","node":"0+4+3","leaf":true},{"id":30,"o":20036,"text":"Mere efterbehandling","url":"multiple_finishing.html","node":"0+4+4","leaf":true},{"id":31,"o":20032,"text":"DFA-efterbehandlerprofiler","url":"custom_finishing.html","node":"0+4+5","leaf":true},{"id":32,"o":28683,"text":"Skilleark","url":"slip_sheets.html","node":"0+4+6","leaf":true},{"id":33,"o":20038,"text":"Forskydning/undersæt","url":"offset_subset.html","node":"0+4+7","leaf":true},{"id":34,"o":20040,"text":"Oprettelse af blok","url":"pads.html","node":"0+4+8","leaf":true},{"id":35,"o":19588,"text":"Pjecer","url":"booklet_creation.html","node":"0+4+9","leaf":true}]},{"id":36,"o":36305,"text":"Udfaldsbakke","url":"output_destination.html","node":"0+5","leaf":true}]},{"id":37,"o":19612,"text":"Specialsider","url":"special_pages.html","node":"1","children":[{"id":38,"o":19613,"text":"Tilføj omslag","url":"add_covers.html","node":"1+0","leaf":true},{"id":39,"o":19617,"text":"Tilføj indsæt","url":"add_inserts.html","node":"1+1","leaf":true},{"id":40,"o":36116,"text":"Tilføj undtagelser","url":"add_exceptions.html","node":"1+2","leaf":true}]},{"id":41,"o":20646,"text":"Billedkvalitet","url":"image_options.html","node":"2","children":[{"id":42,"o":57766,"text":"Farveoversigt","url":"color_summary.html","node":"2+0","leaf":true},{"id":43,"o":56155,"text":"Yderligere Spot Colorant (farvekorrigering)","url":"additional_spot_colorant.html","node":"2+1","children":[{"id":44,"o":56959,"text":"Gennemsigtig toner","url":"clear_dry_ink.html","node":"2+1+0","leaf":true}]},{"id":45,"o":19757,"text":"Anti-aliasing","url":"anti_aliasing.html","node":"2+2","leaf":true},{"id":46,"o":19755,"text":"Bruger TRC","url":"user_trcs.html","node":"2+3","leaf":true},{"id":47,"o":19768,"text":"Opløsning","url":"resolution.html","node":"2+4","leaf":true},{"id":48,"o":19761,"text":"Rasterering","url":"halftone_screen.html","node":"2+5","leaf":true},{"id":49,"o":36261,"text":"Tonersparer","url":"toner_saver.html","node":"2+6","leaf":true},{"id":50,"o":19765,"text":"Billedforskydning","url":"image_shift.html","node":"2+7","leaf":true},{"id":51,"o":19767,"text":"Lysstyrke","url":"lightness.html","node":"2+8","leaf":true}]},{"id":52,"o":19810,"text":"Opgavekommentarer","url":"job_notes.html","node":"3","leaf":true},{"id":53,"o":36358,"text":"Pjece/vandmærke","url":"booklet_watermark.html","node":"4","children":[{"id":54,"o":35295,"text":"Pjeceindstillinger","url":"booklet_options.html","node":"4+0","leaf":true},{"id":55,"o":35301,"text":"Redigering af vandmærke","url":"watermark_editor.html","node":"4+1","leaf":true},{"id":56,"o":19708,"text":"Baggrundsformular","url":"background_form.html","node":"4+2","leaf":true}]},{"id":57,"o":36108,"text":"Udvidet","url":"advanced.html","node":"5","children":[{"id":58,"o":19659,"text":"Pjecerækkefølge","url":"booklet_image_order.html","node":"5+0","leaf":true},{"id":59,"o":20617,"text":"Roter 180 grader","url":"rotate_image.html","node":"5+1","leaf":true},{"id":60,"o":36069,"text":"Opgave-ID","url":"job_id.html","node":"5+2","children":[{"id":61,"o":36066,"text":"Brug foranstående sider","url":"leading_pages.html","node":"5+2+0","leaf":true}]},{"id":62,"o":19676,"text":"Outputfunktioner","url":"output_options.html","node":"5+3","leaf":true},{"id":63,"o":19668,"text":"Spejlvendt output","url":"mirrored_output.html","node":"5+4","leaf":true},{"id":64,"o":19665,"text":"Xerox-opgavebillet","url":"job_ticket.html","node":"5+5","leaf":true},{"id":65,"o":19670,"text":"Negativt output","url":"negative_output.html","node":"5+6","leaf":true},{"id":66,"o":35617,"text":"Justér linjevægt","url":"adjust_line_weight.html","node":"5+7","leaf":true},{"id":67,"o":19674,"text":"OPI-erstatning","url":"opi_substitution.html","node":"5+8","leaf":true},{"id":68,"o":19672,"text":"OPI-forscanning","url":"opi_prescan.html","node":"5+9","leaf":true},{"id":69,"o":19661,"text":"Tving til nyt papirformat","url":"force_new_paper_size.html","node":"5+10","leaf":true},{"id":70,"o":35293,"text":"Sider til udskrivning","url":"pages_to_print.html","node":"5+11","leaf":true},{"id":71,"o":19682,"text":"Kontering","url":"accounting.html","node":"5+12","children":[{"id":72,"o":36683,"text":"Konteringsmeddelelse","url":"accounting_prompt.html","node":"5+12+0","leaf":true}]},{"id":73,"o":35292,"text":"Tovejskommunikation","url":"bi-di.html","node":"5+13","leaf":true}]},{"id":74,"o":3293,"text":"Copyright","url":"copyright.html","node":"6","leaf":true}]